idigbio/__init__.py
idigbio/json_client.py
idigbio/pandas_client.py
idigbio/util.py
idigbio-0.8.0.dist-info/DESCRIPTION.rst
idigbio-0.8.0.dist-info/METADATA
idigbio-0.8.0.dist-info/RECORD
idigbio-0.8.0.dist-info/WHEEL
idigbio-0.8.0.dist-info/metadata.json
idigbio-0.8.0.dist-info/top_level.txt
