Metadata-Version: 2.0
Name: idigbio
Version: 0.8.0
Summary: Python Client for the iDigBio Search API
Home-page: http://github.com/idigbio/idigbio-python-client/
Author: Alex Thompson
Author-email: godfoder@acis.ufl.edu
License: MIT
Platform: UNKNOWN
Classifier: Development Status :: 5 - Production/Stable
Classifier: Intended Audience :: Developers
Classifier: Natural Language :: English
Classifier: License :: OSI Approved :: MIT License
Classifier: Operating System :: OS Independent
Classifier: Programming Language :: Python
Classifier: Programming Language :: Python :: 2.7
Classifier: Programming Language :: Python :: 3
Classifier: Programming Language :: Python :: 3.3
Classifier: Programming Language :: Python :: 3.4
Classifier: Programming Language :: Python :: 3.5
Classifier: Topic :: Software Development :: Libraries :: Python Modules
Requires-Dist: requests
Provides-Extra: pandas
Requires-Dist: pandas; extra == 'pandas'
